heimdallr/__init__.py
heimdallr/configuration/__init__.py
heimdallr/configuration/heimdallr_config.py
heimdallr/configuration/heimdallr_settings.py
heimdallr/entry_points/__init__.py
heimdallr/entry_points/cli.py
heimdallr/entry_points/publisher.py
heimdallr/entry_points/repl.py
heimdallr/entry_points/server.py
heimdallr/entry_points/deprecated/__init__.py
heimdallr/entry_points/deprecated/publisher_non_sch.py
heimdallr/server/__init__.py
heimdallr/server/board_layout/__init__.py
heimdallr/server/board_layout/body.py
heimdallr/server/board_layout/footer.py
heimdallr/server/board_layout/header.py
heimdallr/server/board_layout/menu.py
heimdallr/server/board_layout/root_layout.py
heimdallr/utilities/__init__.py
heimdallr/utilities/date_tools.py
heimdallr/utilities/nvidia/__init__.py
heimdallr/utilities/nvidia/bindings.py
heimdallr/utilities/nvidia/packing.py
heimdallr/utilities/nvidia/smi_parsing.py
heimdallr/utilities/publisher/__init__.py
heimdallr/utilities/publisher/system_resources.py
heimdallr/utilities/publisher/unpacking.py
heimdallr/utilities/publisher/windows_task_scheduler_utilities.py
heimdallr/utilities/server/__init__.py
heimdallr/utilities/server/du_utilities.py
heimdallr/utilities/server/github_org_generators.py
heimdallr/utilities/server/google_calendar.py
heimdallr/utilities/server/gpu_utilities.py
heimdallr/utilities/server/meet_status.py
heimdallr/utilities/server/slack_status.py
heimdallr/utilities/server/teams_status.py
Heimdallr-0.2.8.dist-info/LICENSE.md
Heimdallr-0.2.8.dist-info/METADATA
Heimdallr-0.2.8.dist-info/WHEEL
Heimdallr-0.2.8.dist-info/entry_points.txt
Heimdallr-0.2.8.dist-info/top_level.txt
Heimdallr-0.2.8.dist-info/RECORD
